[{"id":109344,"Name":"Balakliya","state_id":4686,"state_code":"63","state_name":"Kharkivska oblast","country_id":230,"country_code":"UA","country_name":"Ukraine","latitude":"49.46270000","longitude":"36.85951000","wikiDataId":"Q986263"},{"id":109352,"Name":"Barvinkove","state_id":4686,"state_code":"63","state_name":"Kharkivska oblast","country_id":230,"country_code":"UA","country_name":"Ukraine","latitude":"48.90970000","longitude":"37.02051000","wikiDataId":"Q809665"},{"id":109380,"Name":"Berezivka","state_id":4686,"state_code":"63","state_name":"Kharkivska oblast","country_id":230,"country_code":"UA","country_name":"Ukraine","latitude":"49.43935000","longitude":"35.70736000","wikiDataId":"Q4084595"},{"id":109390,"Name":"Bezlyudivka","state_id":4686,"state_code":"63","state_name":"Kharkivska oblast","country_id":230,"country_code":"UA","country_name":"Ukraine","latitude":"49.87547000","longitude":"36.26539000","wikiDataId":"Q829969"},{"id":109413,"Name":"Blyznyuky","state_id":4686,"state_code":"63","state_name":"Kharkivska oblast","country_id":230,"country_code":"UA","country_name":"Ukraine","latitude":"48.85775000","longitude":"36.55505000","wikiDataId":"Q4088167"},{"id":109419,"Name":"Bohodukhiv","state_id":4686,"state_code":"63","state_name":"Kharkivska oblast","country_id":230,"country_code":"UA","country_name":"Ukraine","latitude":"50.16466000","longitude":"35.52765000","wikiDataId":"Q889930"},{"id":109432,"Name":"Borova","state_id":4686,"state_code":"63","state_name":"Kharkivska oblast","country_id":230,"country_code":"UA","country_name":"Ukraine","latitude":"49.37770000","longitude":"37.62136000","wikiDataId":"Q2010649"},{"id":109458,"Name":"Budy","state_id":4686,"state_code":"63","state_name":"Kharkivska oblast","country_id":230,"country_code":"UA","country_name":"Ukraine","latitude":"49.89133000","longitude":"36.02096000","wikiDataId":"Q4098214"},{"id":109469,"Name":"Chapayeve","state_id":4686,"state_code":"63","state_name":"Kharkivska oblast","country_id":230,"country_code":"UA","country_name":"Ukraine","latitude":"49.36625000","longitude":"35.87486000","wikiDataId":"Q4507184"},{"id":109504,"Name":"Chervonyy Oskil","state_id":4686,"state_code":"63","state_name":"Kharkivska oblast","country_id":230,"country_code":"UA","country_name":"Ukraine","latitude":"49.17906000","longitude":"37.42593000","wikiDataId":"Q664445"},{"id":109522,"Name":"Chuhuyiv","state_id":4686,"state_code":"63","state_name":"Kharkivska oblast","country_id":230,"country_code":"UA","country_name":"Ukraine","latitude":"49.83588000","longitude":"36.68803000","wikiDataId":"Q889618"},{"id":109539,"Name":"Derhachi","state_id":4686,"state_code":"63","state_name":"Kharkivska oblast","country_id":230,"country_code":"UA","country_name":"Ukraine","latitude":"50.10659000","longitude":"36.12112000","wikiDataId":"Q1106109"},{"id":109590,"Name":"Dvorichna","state_id":4686,"state_code":"63","state_name":"Kharkivska oblast","country_id":230,"country_code":"UA","country_name":"Ukraine","latitude":"49.85019000","longitude":"37.68262000","wikiDataId":"Q4156149"},{"id":109596,"Name":"Eskhar","state_id":4686,"state_code":"63","state_name":"Kharkivska oblast","country_id":230,"country_code":"UA","country_name":"Ukraine","latitude":"49.79614000","longitude":"36.59047000","wikiDataId":"Q4119426"},{"id":109663,"Name":"Huty","state_id":4686,"state_code":"63","state_name":"Kharkivska oblast","country_id":230,"country_code":"UA","country_name":"Ukraine","latitude":"50.13322000","longitude":"35.34394000","wikiDataId":"Q4153056"},{"id":109691,"Name":"Izyum","state_id":4686,"state_code":"63","state_name":"Kharkivska oblast","country_id":230,"country_code":"UA","country_name":"Ukraine","latitude":"49.20875000","longitude":"37.24849000","wikiDataId":"Q841029"},{"id":109724,"Name":"Kehychivka","state_id":4686,"state_code":"63","state_name":"Kharkivska oblast","country_id":230,"country_code":"UA","country_name":"Ukraine","latitude":"49.28656000","longitude":"35.76153000","wikiDataId":"Q4218839"},{"id":109727,"Name":"Kharkiv","state_id":4686,"state_code":"63","state_name":"Kharkivska oblast","country_id":230,"country_code":"UA","country_name":"Ukraine","latitude":"49.98081000","longitude":"36.25272000","wikiDataId":"Q42308"},{"id":109736,"Name":"Khorosheve","state_id":4686,"state_code":"63","state_name":"Kharkivska oblast","country_id":230,"country_code":"UA","country_name":"Ukraine","latitude":"49.85413000","longitude":"36.21704000","wikiDataId":"Q4500117"},{"id":109757,"Name":"Kivsharivka","state_id":4686,"state_code":"63","state_name":"Kharkivska oblast","country_id":230,"country_code":"UA","country_name":"Ukraine","latitude":"49.63096000","longitude":"37.68821000","wikiDataId":"Q4225908"},{"id":109767,"Name":"Kochetok","state_id":4686,"state_code":"63","state_name":"Kharkivska oblast","country_id":230,"country_code":"UA","country_name":"Ukraine","latitude":"49.88005000","longitude":"36.73723000","wikiDataId":"Q4236779"},{"id":109775,"Name":"Kolomak","state_id":4686,"state_code":"63","state_name":"Kharkivska oblast","country_id":230,"country_code":"UA","country_name":"Ukraine","latitude":"49.83987000","longitude":"35.30441000","wikiDataId":"Q1996113"},{"id":109804,"Name":"Korotych","state_id":4686,"state_code":"63","state_name":"Kharkivska oblast","country_id":230,"country_code":"UA","country_name":"Ukraine","latitude":"49.94737000","longitude":"36.03736000","wikiDataId":"Q4234163"},{"id":109838,"Name":"Krasnohrad","state_id":4686,"state_code":"63","state_name":"Kharkivska oblast","country_id":230,"country_code":"UA","country_name":"Ukraine","latitude":"49.38009000","longitude":"35.44186000","wikiDataId":"Q1104739"},{"id":109841,"Name":"Krasnokuts’k","state_id":4686,"state_code":"63","state_name":"Kharkivska oblast","country_id":230,"country_code":"UA","country_name":"Ukraine","latitude":"50.06602000","longitude":"35.16275000","wikiDataId":"Q4238800"},{"id":109843,"Name":"Krasnopavlivka","state_id":4686,"state_code":"63","state_name":"Kharkivska oblast","country_id":230,"country_code":"UA","country_name":"Ukraine","latitude":"49.13643000","longitude":"36.31911000","wikiDataId":"Q4238883"},{"id":109886,"Name":"Kulynychi","state_id":4686,"state_code":"63","state_name":"Kharkivska oblast","country_id":230,"country_code":"UA","country_name":"Ukraine","latitude":"49.98178000","longitude":"36.38283000","wikiDataId":"Q4246308"},{"id":109887,"Name":"Kupjansk","state_id":4686,"state_code":"63","state_name":"Kharkivska oblast","country_id":230,"country_code":"UA","country_name":"Ukraine","latitude":"49.71055000","longitude":"37.61517000","wikiDataId":"Q889555"},{"id":109932,"Name":"Lozova","state_id":4686,"state_code":"63","state_name":"Kharkivska oblast","country_id":230,"country_code":"UA","country_name":"Ukraine","latitude":"48.88937000","longitude":"36.31755000","wikiDataId":"Q889630"},{"id":109951,"Name":"Lyman","state_id":4686,"state_code":"63","state_name":"Kharkivska oblast","country_id":230,"country_code":"UA","country_name":"Ukraine","latitude":"49.59769000","longitude":"36.47030000","wikiDataId":"Q4261659"},{"id":109966,"Name":"Lyubotyn","state_id":4686,"state_code":"63","state_name":"Kharkivska oblast","country_id":230,"country_code":"UA","country_name":"Ukraine","latitude":"49.94691000","longitude":"35.92907000","wikiDataId":"Q889542"},{"id":109979,"Name":"Mala Danylivka","state_id":4686,"state_code":"63","state_name":"Kharkivska oblast","country_id":230,"country_code":"UA","country_name":"Ukraine","latitude":"50.06354000","longitude":"36.16564000","wikiDataId":"Q4276832"},{"id":109990,"Name":"Malynivka","state_id":4686,"state_code":"63","state_name":"Kharkivska oblast","country_id":230,"country_code":"UA","country_name":"Ukraine","latitude":"49.81667000","longitude":"36.73333000","wikiDataId":"Q4277906"},{"id":109991,"Name":"Manchenky","state_id":4686,"state_code":"63","state_name":"Kharkivska oblast","country_id":230,"country_code":"UA","country_name":"Ukraine","latitude":"49.97982000","longitude":"35.85835000","wikiDataId":"Q4280798"},{"id":110023,"Name":"Merefa","state_id":4686,"state_code":"63","state_name":"Kharkivska oblast","country_id":230,"country_code":"UA","country_name":"Ukraine","latitude":"49.82302000","longitude":"36.05069000","wikiDataId":"Q1019408"},{"id":110110,"Name":"Nova Vodolaha","state_id":4686,"state_code":"63","state_name":"Kharkivska oblast","country_id":230,"country_code":"UA","country_name":"Ukraine","latitude":"49.71901000","longitude":"35.86578000","wikiDataId":"Q4321992"},{"id":110141,"Name":"Novopokrovka","state_id":4686,"state_code":"63","state_name":"Kharkivska oblast","country_id":230,"country_code":"UA","country_name":"Ukraine","latitude":"49.83349000","longitude":"36.54771000","wikiDataId":"Q4324986"},{"id":110222,"Name":"Panyutyne","state_id":4686,"state_code":"63","state_name":"Kharkivska oblast","country_id":230,"country_code":"UA","country_name":"Ukraine","latitude":"48.93692000","longitude":"36.27563000","wikiDataId":"Q4344568"},{"id":110242,"Name":"Peresichna","state_id":4686,"state_code":"63","state_name":"Kharkivska oblast","country_id":230,"country_code":"UA","country_name":"Ukraine","latitude":"50.02452000","longitude":"35.97871000","wikiDataId":"Q4350907"},{"id":110247,"Name":"Pervomaiskyi Raion","state_id":4686,"state_code":"63","state_name":"Kharkivska oblast","country_id":230,"country_code":"UA","country_name":"Ukraine","latitude":"49.41667000","longitude":"36.33333000","wikiDataId":"Q1975932"},{"id":110252,"Name":"Pervomays’kyy","state_id":4686,"state_code":"63","state_name":"Kharkivska oblast","country_id":230,"country_code":"UA","country_name":"Ukraine","latitude":"49.38742000","longitude":"36.21471000","wikiDataId":"Q889579"},{"id":110257,"Name":"Petrivs’ke","state_id":4686,"state_code":"63","state_name":"Kharkivska oblast","country_id":230,"country_code":"UA","country_name":"Ukraine","latitude":"49.17695000","longitude":"36.89999000","wikiDataId":"Q4361307"},{"id":110275,"Name":"Pivdenne","state_id":4686,"state_code":"63","state_name":"Kharkivska oblast","country_id":230,"country_code":"UA","country_name":"Ukraine","latitude":"49.88315000","longitude":"36.06785000","wikiDataId":"Q785296"},{"id":110290,"Name":"Pokotylivka","state_id":4686,"state_code":"63","state_name":"Kharkivska oblast","country_id":230,"country_code":"UA","country_name":"Ukraine","latitude":"49.91343000","longitude":"36.17511000","wikiDataId":"Q4369132"},{"id":110317,"Name":"Prudyanka","state_id":4686,"state_code":"63","state_name":"Kharkivska oblast","country_id":230,"country_code":"UA","country_name":"Ukraine","latitude":"50.23606000","longitude":"36.16835000","wikiDataId":"Q4382534"},{"id":110319,"Name":"Prykolotne","state_id":4686,"state_code":"63","state_name":"Kharkivska oblast","country_id":230,"country_code":"UA","country_name":"Ukraine","latitude":"50.16273000","longitude":"37.34524000","wikiDataId":"Q4378480"},{"id":110401,"Name":"Sakhnovshchyna","state_id":4686,"state_code":"63","state_name":"Kharkivska oblast","country_id":230,"country_code":"UA","country_name":"Ukraine","latitude":"49.15166000","longitude":"35.87198000","wikiDataId":"Q4409547"},{"id":110411,"Name":"Savyntsi","state_id":4686,"state_code":"63","state_name":"Kharkivska oblast","country_id":230,"country_code":"UA","country_name":"Ukraine","latitude":"49.40257000","longitude":"37.06266000","wikiDataId":"Q4404036"},{"id":110445,"Name":"Shevchenkove","state_id":4686,"state_code":"63","state_name":"Kharkivska oblast","country_id":230,"country_code":"UA","country_name":"Ukraine","latitude":"49.69585000","longitude":"37.17348000","wikiDataId":"Q1002607"},{"id":110476,"Name":"Slatyne","state_id":4686,"state_code":"63","state_name":"Kharkivska oblast","country_id":230,"country_code":"UA","country_name":"Ukraine","latitude":"50.21041000","longitude":"36.15376000","wikiDataId":"Q4423206"},{"id":110484,"Name":"Slobozhans’ke","state_id":4686,"state_code":"63","state_name":"Kharkivska oblast","country_id":230,"country_code":"UA","country_name":"Ukraine","latitude":"49.59701000","longitude":"36.52618000","wikiDataId":"Q4230273"},{"id":110511,"Name":"Solonytsivka","state_id":4686,"state_code":"63","state_name":"Kharkivska oblast","country_id":230,"country_code":"UA","country_name":"Ukraine","latitude":"49.99682000","longitude":"36.03464000","wikiDataId":"Q4428376"},{"id":110540,"Name":"Staryy Merchyk","state_id":4686,"state_code":"63","state_name":"Kharkivska oblast","country_id":230,"country_code":"UA","country_name":"Ukraine","latitude":"49.98147000","longitude":"35.75904000","wikiDataId":"Q4441101"},{"id":110541,"Name":"Staryy Saltiv","state_id":4686,"state_code":"63","state_name":"Kharkivska oblast","country_id":230,"country_code":"UA","country_name":"Ukraine","latitude":"50.07619000","longitude":"36.78852000","wikiDataId":"Q4441136"},{"id":110558,"Name":"Studenok","state_id":4686,"state_code":"63","state_name":"Kharkivska oblast","country_id":230,"country_code":"UA","country_name":"Ukraine","latitude":"49.09107000","longitude":"37.48697000","wikiDataId":"Q4444512"},{"id":110663,"Name":"Utkivka","state_id":4686,"state_code":"63","state_name":"Kharkivska oblast","country_id":230,"country_code":"UA","country_name":"Ukraine","latitude":"49.78583000","longitude":"36.07528000","wikiDataId":"Q4478919"},{"id":110670,"Name":"Valky","state_id":4686,"state_code":"63","state_name":"Kharkivska oblast","country_id":230,"country_code":"UA","country_name":"Ukraine","latitude":"49.83597000","longitude":"35.61223000","wikiDataId":"Q1104747"},{"id":110680,"Name":"Vasyshcheve","state_id":4686,"state_code":"63","state_name":"Kharkivska oblast","country_id":230,"country_code":"UA","country_name":"Ukraine","latitude":"49.82852000","longitude":"36.32691000","wikiDataId":"Q4105050"},{"id":110696,"Name":"Velykyy Burluk","state_id":4686,"state_code":"63","state_name":"Kharkivska oblast","country_id":230,"country_code":"UA","country_name":"Ukraine","latitude":"50.06170000","longitude":"37.38373000","wikiDataId":"Q1965817"},{"id":110699,"Name":"Verbivka","state_id":4686,"state_code":"63","state_name":"Kharkivska oblast","country_id":230,"country_code":"UA","country_name":"Ukraine","latitude":"49.41667000","longitude":"35.53333000","wikiDataId":"Q4107475"},{"id":110747,"Name":"Vovchans’k","state_id":4686,"state_code":"63","state_name":"Kharkivska oblast","country_id":230,"country_code":"UA","country_name":"Ukraine","latitude":"50.29078000","longitude":"36.94108000","wikiDataId":"Q1104773"},{"id":110754,"Name":"Vvedenka","state_id":4686,"state_code":"63","state_name":"Kharkivska oblast","country_id":230,"country_code":"UA","country_name":"Ukraine","latitude":"49.82372000","longitude":"36.50264000","wikiDataId":"Q4105600"},{"id":110768,"Name":"Vysokyy","state_id":4686,"state_code":"63","state_name":"Kharkivska oblast","country_id":230,"country_code":"UA","country_name":"Ukraine","latitude":"49.89156000","longitude":"36.12175000","wikiDataId":"Q4129291"},{"id":110807,"Name":"Zachepylivka","state_id":4686,"state_code":"63","state_name":"Kharkivska oblast","country_id":230,"country_code":"UA","country_name":"Ukraine","latitude":"49.19385000","longitude":"35.23943000","wikiDataId":"Q2010641"},{"id":110857,"Name":"Zmiyiv","state_id":4686,"state_code":"63","state_name":"Kharkivska oblast","country_id":230,"country_code":"UA","country_name":"Ukraine","latitude":"49.67453000","longitude":"36.34775000","wikiDataId":"Q1106097"},{"id":110859,"Name":"Zolochiv","state_id":4686,"state_code":"63","state_name":"Kharkivska oblast","country_id":230,"country_code":"UA","country_name":"Ukraine","latitude":"50.27985000","longitude":"35.98179000","wikiDataId":"Q2010577"}]